weathercatcher/__init__.py
weathercatcher/wc.py
weathercatcher-1.0.1.3.dist-info/METADATA
weathercatcher-1.0.1.3.dist-info/WHEEL
weathercatcher-1.0.1.3.dist-info/top_level.txt
weathercatcher-1.0.1.3.dist-info/RECORD
