Metadata-Version: 2.1
Name: weathercatcher
Version: 1.0.1.3
Summary: Module to catch weather
Home-page: https://github.com/smartwe/weathercatcher
Author: smartwe
Author-email: sparklingwee@naver.com
License: MIT
Platform: UNKNOWN
Requires-Python: >=3
Requires-Dist: bs4
